nium/__init__.py
nium/api_client.py
nium/api_response.py
nium/configuration.py
nium/exceptions.py
nium/py.typed
nium/rest.py
nium/api/__init__.py
nium/api/beneficiary_api.py
nium/api/cards_reference_data_api.py
nium/api/client_prefund_account_api.py
nium/api/client_settings_api.py
nium/api/client_transactions_api.py
nium/api/controls_api.py
nium/api/conversions_api.py
nium/api/conversions_previous_version_api.py
nium/api/customer_account_corporate_api.py
nium/api/customer_account_individual_api.py
nium/api/customer_fees_api.py
nium/api/customer_funding_api.py
nium/api/customer_management_api.py
nium/api/customer_terms_and_conditions_api.py
nium/api/customer_virtual_accounts_api.py
nium/api/customer_wallet_balance_api.py
nium/api/customer_wallet_transactions_api.py
nium/api/lifecycle_api.py
nium/api/new_corporate_apis_api.py
nium/api/open_banking_onboarding_api.py
nium/api/payin_api.py
nium/api/payout_api.py
nium/api/payout_controller_api.py
nium/api/quotes_api.py
nium/api/quotes_previous_version_api.py
nium/api/rates_api.py
nium/api/reference_data_api.py
nium/api/security_api.py
nium/api/simulators_api.py
nium/api/three_ds_api.py
nium/api/wallet_to_wallet_transfers_api.py
nium/models/__init__.py
nium/models/access.py
nium/models/account.py
nium/models/account_reference.py
nium/models/account_response_dto.py
nium/models/account_status_response.py
nium/models/account_validation_request_dto.py
nium/models/account_validation_response_dto.py
nium/models/activate_card_request_v2_dto.py
nium/models/activate_card_response_dto.py
nium/models/activate_card_response_v2_dto.py
nium/models/add_beneficiary_request.py
nium/models/add_beneficiary_request_dto.py
nium/models/add_card_request.py
nium/models/add_card_request_v2.py
nium/models/add_card_response_dto.py
nium/models/add_card_v2_response_dto.py
nium/models/add_category_response_dto.py
nium/models/add_customer_request_dto.py
nium/models/add_customer_response_dto.py
nium/models/additional_fees_dto.py
nium/models/address.py
nium-1.0.0.dist-info/LICENSE
nium-1.0.0.dist-info/METADATA
nium-1.0.0.dist-info/WHEEL
nium-1.0.0.dist-info/top_level.txt
nium-1.0.0.dist-info/RECORD
