Metadata-Version: 2.1
Name: nium
Version: 1.0.0
Summary: NIUM Platform
Home-page: 
Author: NIUM Platform
Author-email: experience@nium.com
License: Copyright (c) 2023 NIUM
Keywords: NIUM Platform
License-File: LICENSE
Requires-Dist: urllib3 <2.1.0,>=1.25.3
Requires-Dist: python-dateutil
Requires-Dist: pydantic <2,>=1.10.5
Requires-Dist: aenum
